{
  "db_name": "PostgreSQL",
  "query": "\n        SELECT COUNT(*) as \"count!\"\n        FROM session_refresh_tokens\n        WHERE user_id = $1\n          AND is_revoked = FALSE\n          AND expires_at > NOW()\n        ",
  "describe": {
    "columns": [
      {
        "ordinal": 0,
        "name": "count!",
        "type_info": "Int8"
      }
    ],
    "parameters": {
      "Left": [
        "Int8"
      ]
    },
    "nullable": [
      null
    ]
  },
  "hash": "b5b569ecae7c56e911a7d70277154fbfbd765f933d6a0fe0cd8817ac7cfb3117"
}
